fourim/__init__.py
fourim/main.py
fourim/backend/__init__.py
fourim/backend/components.py
fourim/backend/compute.py
fourim/backend/utils.py
fourim/config/components.yaml
fourim/config/options.py
fourim/config/parameters.toml
fourim/gui/__init__.py
fourim/gui/main.py
fourim/gui/plot.py
fourim/gui/scrollbar.py
fourim/gui/settings.py
fourim/gui/slider.py
fourim-1.4.5.dist-info/licenses/LICENSE
fourim-1.4.5.dist-info/METADATA
fourim-1.4.5.dist-info/WHEEL
fourim-1.4.5.dist-info/entry_points.txt
fourim-1.4.5.dist-info/top_level.txt
fourim-1.4.5.dist-info/RECORD
