Metadata-Version: 2.4
Name: fourim
Version: 1.4.5
Summary: A tool for visualization of diverse fourier transformations.
Author-email: Marten Scheuck <martenscheuck@gmail.com>
License: The MIT License (MIT)
Project-URL: repository, https://github.com/MBSck/fourim
Keywords: astronomy,interferometry,visualisation,fourier
Classifier: Development Status :: 4 - Beta
Classifier: Framework :: Sphinx
Classifier: License :: OSI Approved :: MIT License
Classifier: Natural Language :: English
Classifier: Operating System :: OS Independent
Classifier: Programming Language :: Python :: 3
Classifier: Programming Language :: Python :: 3.10
Classifier: Topic :: Scientific/Engineering :: Astronomy
Classifier: Topic :: Scientific/Engineering :: Physics
Requires-Python: >=3.10
License-File: LICENSE
Requires-Dist: astropy>=5.1
Requires-Dist: astroquery>=0.4.6
Requires-Dist: pandas>=1.5.2
Requires-Dist: matplotlib>=3.5.3
Requires-Dist: numpy>=1.23.2
Requires-Dist: scipy>=1.9.1
Requires-Dist: tqdm>=4.64.0
Requires-Dist: pyside6>=6.8.1.1
Requires-Dist: toml>=0.10.2
Requires-Dist: pyyaml>=6.0.2
Provides-Extra: dev
Requires-Dist: ipython; extra == "dev"
Requires-Dist: pytest>=7.2.1; extra == "dev"
Requires-Dist: pytest-cov>=4.0.0; extra == "dev"
Requires-Dist: sphinx==7.0.1; extra == "dev"
Requires-Dist: sphinx-autobuild==2021.3.14; extra == "dev"
Requires-Dist: sphinx-autodoc-typehints==1.23; extra == "dev"
Requires-Dist: pydata-sphinx-theme==0.13.3; extra == "dev"
Requires-Dist: numpydoc==1.5.0; extra == "dev"
Dynamic: license-file
